PySpot-1.2.dist-info/METADATA
PySpot-1.2.dist-info/RECORD
PySpot-1.2.dist-info/WHEEL
PySpot-1.2.dist-info/top_level.txt
pyspot/__init__.py
pyspot/api_timer.py
pyspot/auth.py
pyspot/credentials_auth.py
pyspot/session.py
pyspot/user_auth.py
tests/__init__.py
tests/test_classes.py
