Metadata-Version: 2.1
Name: PySpot
Version: 1.2
Summary: A Python implementation of the HubSpot API
Home-page: https://github.com/EdMan1022/PySpot.git
Author: Edward Brennan
Author-email: EdMan1022@gmail.com
License: UNKNOWN
Platform: UNKNOWN
Classifier: Programming Language :: Python :: 3
Classifier: License :: OSI Approved :: MIT License
Classifier: Operating System :: OS Independent
Requires-Dist: requests
